sister/__init__.py
sister/core.py
sister/download.py
sister/tokenizers.py
sister/word_embedders.py
sister-0.2.2.dist-info/WHEEL
sister-0.2.2.dist-info/METADATA
sister-0.2.2.dist-info/RECORD
