Metadata-Version: 2.1
Name: sister
Version: 0.2.2
Summary: SISTER (SImple SenTence EmbeddeR)
Author: sobamchan
Author-email: oh.sore.sore.soutarou@gmail.com
Requires-Python: >=3.8,<4.0
Classifier: Programming Language :: Python :: 3
Classifier: Programming Language :: Python :: 3.8
Classifier: Programming Language :: Python :: 3.9
Requires-Dist: Janome (==0.3.10)
Requires-Dist: fasttext (==0.9.2)
Requires-Dist: gensim (==3.8.3)
Requires-Dist: mecab-python3 (==0.996.5)
Requires-Dist: numpy (==1.19.0)
Requires-Dist: progressbar (>=2.5,<3.0)
Requires-Dist: torch (==1.5.1)
Requires-Dist: transformers (==2.11.0)
